docxedit.py
docxedit-1.0.4.dist-info/METADATA
docxedit-1.0.4.dist-info/WHEEL
docxedit-1.0.4.dist-info/licenses/LICENSE.txt
docxedit-1.0.4.dist-info/RECORD
