Metadata-Version: 2.3
Name: docxedit
Version: 1.0.4
Summary: Edit Word documents but keep original formatting
Project-URL: Homepage, https://github.com/henrihapponen/docxedit
Project-URL: Bug Tracker, https://github.com/henrihapponen/docxedit/issues
Author-email: Henri Happonen <henkka.happonen@gmail.com>
License-Expression: MIT
License-File: LICENSE.txt
Keywords: document,docx,edit,formatting,python-docx,word
Classifier: License :: OSI Approved :: MIT License
Classifier: Operating System :: OS Independent
Classifier: Programming Language :: Python :: 3
Requires-Python: >=3.7
Requires-Dist: python-docx>=0.8.0
